ws_sdk/__init__.py
ws_sdk/_version.py
ws_sdk/app.py
ws_sdk/client.py
ws_sdk/generator.py
ws_sdk/web.py
ws_sdk/ws_constants.py
ws_sdk/ws_errors.py
ws_sdk/ws_utilities.py
ws_sdk/tests/__init__.py
ws_sdk/tests/test_app.py
ws_sdk/tests/test_client.py
ws_sdk/tests/test_ws_utilities.py
ws_sdk-23.12.2.dist-info/LICENSE
ws_sdk-23.12.2.dist-info/METADATA
ws_sdk-23.12.2.dist-info/WHEEL
ws_sdk-23.12.2.dist-info/top_level.txt
ws_sdk-23.12.2.dist-info/RECORD
