Metadata-Version: 2.1
Name: ws-sdk
Version: 23.12.2
Summary: WS Python SDK
Home-page: https://github.com/whitesource-ps/ws-sdk
Author: WhiteSource Professional Services
Author-email: ps@whitesourcesoftware.com
License: LICENSE
Platform: UNKNOWN
Classifier: Programming Language :: Python :: 3.7
Classifier: Programming Language :: Python :: 3.8
Classifier: Programming Language :: Python :: 3.9
Classifier: License :: OSI Approved :: Apache Software License
Classifier: Operating System :: OS Independent
Requires-Python: >=3.7
License-File: LICENSE
Requires-Dist: DateTime ~=4.9
Requires-Dist: requests ~=2.31.0
Requires-Dist: urllib3 ~=2.1.0
Provides-Extra: spdx
Requires-Dist: spdx-tools ; extra == 'spdx'
